turbodl/__init__.py
turbodl/buffers.py
turbodl/cli/__init__.py
turbodl/cli/__main__.py
turbodl/constants.py
turbodl/core.py
turbodl/downloaders.py
turbodl/exceptions.py
turbodl/merger.py
turbodl/py.typed
turbodl/utils.py
turbodl-0.7.0.dist-info/WHEEL
turbodl-0.7.0.dist-info/entry_points.txt
turbodl-0.7.0.dist-info/METADATA
turbodl-0.7.0.dist-info/RECORD
