Metadata-Version: 2.4
Name: turbodl
Version: 0.7.0
Summary: TurboDL is an extremely smart, fast, and efficient download manager designed to optimize your downloading experience.
Keywords: dl,downloader,manager,python,smart,turbodl,download,fast,efficient,cli,tool,utility
Author: henrique-coder
Author-email: henrique-coder <henriquemoreira10fk@gmail.com>
License-Expression: MIT
Classifier: Development Status :: 4 - Beta
Classifier: Environment :: Console
Classifier: Intended Audience :: Developers
Classifier: Intended Audience :: End Users/Desktop
Classifier: License :: OSI Approved :: MIT License
Classifier: Operating System :: OS Independent
Classifier: Programming Language :: Python :: 3 :: Only
Classifier: Programming Language :: Python :: 3.10
Classifier: Programming Language :: Python :: 3.11
Classifier: Programming Language :: Python :: 3.12
Classifier: Programming Language :: Python :: 3.13
Classifier: Programming Language :: Python :: Implementation :: CPython
Classifier: Programming Language :: Python :: Implementation :: PyPy
Classifier: Topic :: Internet
Classifier: Topic :: Internet :: File Transfer Protocol (FTP)
Classifier: Topic :: Internet :: WWW/HTTP
Classifier: Topic :: Software Development :: Libraries
Classifier: Topic :: Software Development :: Libraries :: Python Modules
Classifier: Topic :: System :: Archiving
Classifier: Topic :: Utilities
Classifier: Environment :: Console
Classifier: Typing :: Typed
Requires-Dist: click>=8.2.1
Requires-Dist: httpx>=0.28.1
Requires-Dist: humanfriendly>=10.0
Requires-Dist: psutil>=7.0.0
Requires-Dist: rich>=14.1.0
Requires-Dist: streamsnapper
Requires-Dist: tenacity>=9.1.2
Requires-Dist: typer>=0.16.1
Maintainer: henrique-coder
Maintainer-email: henrique-coder <henriquemoreira10fk@gmail.com>
Requires-Python: >=3.10
Project-URL: Bug Reports, https://github.com/henrique-coder/turbodl/issues
Project-URL: Bug Tracker, https://github.com/henrique-coder/turbodl/issues
Project-URL: Changelog, https://github.com/henrique-coder/turbodl/releases
Project-URL: Documentation, https://github.com/henrique-coder/turbodl/blob/main/README.md
Project-URL: Download, https://pypi.org/project/turbodl
Project-URL: Homepage, https://github.com/henrique-coder/turbodl
Project-URL: Issues, https://github.com/henrique-coder/turbodl/issues
Project-URL: Releases, https://github.com/henrique-coder/turbodl/releases/latest
Project-URL: Repository, https://github.com/henrique-coder/turbodl
Project-URL: Source Code, https://github.com/henrique-coder/turbodl
